{"inkVersion":20,"root":[["\n","^Welcome to heresy! I have been your guide, following you and watching you ",["ev","visit",3,"seq","/ev","ev","du",0,"==","/ev",{"->":".^.s0","c":true},"ev","du",1,"==","/ev",{"->":".^.s1","c":true},"ev","du",2,"==","/ev",{"->":".^.s2","c":true},"nop",{"s0":["pop","^but I must warn you, not everything I say can be trusted.",{"->":"0.2.23"},null],"s1":["pop","^ I can reasure you, I am your friend and want to help you leave this place ",{"->":"0.2.23"},null],"s2":["pop","^ I can see that maybe this is where you belong",{"->":"0.2.23"},null],"#f":5}],"\n",["ev",{"^->":"0.4.$r1"},{"temp=":"$r"},"str",{"->":".^.s"},[{"#n":"$r1"}],"/str","/ev",{"*":"0.c-0","flg":18},{"s":["^UUh, okay. This sounds a bit ominous.",{"->":"$r","var":true},null]}],["ev",{"^->":"0.5.$r1"},{"temp=":"$r"},"str",{"->":".^.s"},[{"#n":"$r1"}],"/str","/ev",{"*":"0.c-1","flg":18},{"s":["^I'm not sure this is where I belong. Can I leave?",{"->":"$r","var":true},null]}],["ev",{"^->":"0.6.$r1"},{"temp=":"$r"},"str",{"->":".^.s"},[{"#n":"$r1"}],"/str","/ev",{"*":"0.c-2","flg":18},{"s":["^Wait, you've been following me? That's a bit creepy.",{"->":"$r","var":true},null]}],["ev",{"^->":"0.7.$r1"},{"temp=":"$r"},"str",{"->":".^.s"},[{"#n":"$r1"}],"/str","/ev",{"*":"0.c-3","flg":18},{"s":["^Okay then, I trust your",{"->":"$r","var":true},null]}],{"c-0":["ev",{"^->":"0.c-0.$r2"},"/ev",{"temp=":"$r"},{"->":"0.4.s"},[{"#n":"$r2"}],"\n",{"->":"Guide"},"ev",{"VAR?":"Heresy"},1,"-",{"VAR=":"Heresy","re":true},"/ev",{"->":"0.g-0"},{"#f":5}],"c-1":["ev",{"^->":"0.c-1.$r2"},"/ev",{"temp=":"$r"},{"->":"0.5.s"},[{"#n":"$r2"}],"\n","ev",{"VAR?":"Heresy"},1,"-",{"VAR=":"Heresy","re":true},"/ev",{"->":"Guide"},{"->":"0.g-0"},{"#f":5}],"c-2":["ev",{"^->":"0.c-2.$r2"},"/ev",{"temp=":"$r"},{"->":"0.6.s"},[{"#n":"$r2"}],"\n","ev",{"VAR?":"Heresy"},1,"+",{"VAR=":"Heresy","re":true},"/ev",{"->":"Guide"},{"->":"0.g-0"},{"#f":5}],"c-3":["ev",{"^->":"0.c-3.$r2"},"/ev",{"temp=":"$r"},{"->":"0.7.s"},[{"#n":"$r2"}],"\n","ev",{"VAR?":"Heresy"},1,"-",{"VAR=":"Heresy","re":true},"/ev",{"->":"Guide"},{"->":"0.g-0"},{"#f":5}],"g-0":["done",{"#f":5}]}],"done",{"Guide":[["^Have you been enjoying yourself? You are approaching the final level of hell and your only chance to leave. Just remember, some of the challenges you'll face may not be as they appear.","\n",["ev",{"^->":"Guide.0.2.$r1"},{"temp=":"$r"},"str",{"->":".^.s"},[{"#n":"$r1"}],"/str","/ev",{"*":".^.^.c-0","flg":18},{"s":["^Can you give me an example?",{"->":"$r","var":true},null]}],{"c-0":["ev",{"^->":"Guide.0.c-0.$r2"},"/ev",{"temp=":"$r"},{"->":".^.^.2.s"},[{"#n":"$r2"}],"\n","ev",{"VAR?":"Heresy"},1,"+",{"VAR=":"Heresy","re":true},"/ev",{"->":"Guide2"},{"#f":5}]}],{"#f":1}],"Guide2":[["^Well, let's say you're playing a puzzle game, and I tell you that you need to match all the colors in a certain pattern. But in reality, you need to match the shapes instead.","\n",["ev",{"^->":"Guide2.0.2.$r1"},{"temp=":"$r"},"str",{"->":".^.s"},[{"#n":"$r1"}],"/str","/ev",{"*":".^.^.c-0","flg":18},{"s":["^So, you're saying that you'll intentionally mislead me?",{"->":"$r","var":true},null]}],{"c-0":["ev",{"^->":"Guide2.0.c-0.$r2"},"/ev",{"temp=":"$r"},{"->":".^.^.2.s"},[{"#n":"$r2"}],"\n",{"->":"Guide3"},{"#f":5}]}],{"#f":1}],"Guide3":[["^Not intentionally, per se. I just want to keep things interesting. Plus, it's all part of the challenge.","\n",["ev",{"^->":"Guide3.0.2.$r1"},{"temp=":"$r"},"str",{"->":".^.s"},[{"#n":"$r1"}],"/str","/ev",{"*":".^.^.c-0","flg":18},{"s":["^Okay, but how am I supposed to trust you when you've already admitted to being untrustworthy?",{"->":"$r","var":true},null]}],{"c-0":["ev",{"^->":"Guide3.0.c-0.$r2"},"/ev",{"temp=":"$r"},{"->":".^.^.2.s"},[{"#n":"$r2"}],"\n",{"->":"Guide4"},{"#f":5}]}],{"#f":1}],"Guide4":[["^Ah, but that's the fun part! You can't trust me, but you also can't win without me. So, you'll have to use your intuition and wit to navigate through the game.","\n",["ev",{"^->":"Guide4.0.2.$r1"},{"temp=":"$r"},"str",{"->":".^.s"},[{"#n":"$r1"}],"/str","/ev",{"*":".^.^.c-0","flg":18},{"s":["^Alright, I guess I'll give it a shot. But can you at least promise me that the game is fair?",{"->":"$r","var":true},null]}],{"c-0":["ev",{"^->":"Guide4.0.c-0.$r2"},"/ev",{"temp=":"$r"},{"->":".^.^.2.s"},[{"#n":"$r2"}],"\n",{"->":"Guide5"},{"#f":5}]}],{"#f":1}],"Guide5":[["^Of course, the game is fair!","\n","ev",true,"/ev",{"VAR=":"End","re":true},["ev",{"^->":"Guide5.0.6.$r1"},{"temp=":"$r"},"str",{"->":".^.s"},[{"#n":"$r1"}],"/str","/ev",{"*":".^.^.c-0","flg":18},{"s":["^I like a challenge! Let's do this!",{"->":"$r","var":true},null]}],["ev",{"^->":"Guide5.0.7.$r1"},{"temp=":"$r"},"str",{"->":".^.s"},[{"#n":"$r1"}],"/str","/ev",{"*":".^.^.c-1","flg":18},{"s":["^Is that even true?",{"->":"$r","var":true},null]}],["ev",{"^->":"Guide5.0.8.$r1"},{"temp=":"$r"},"str",{"->":".^.s"},[{"#n":"$r1"}],"/str","/ev",{"*":".^.^.c-2","flg":18},{"s":["^I don't know... this seems a bit unfair.",{"->":"$r","var":true},null]}],["ev",{"^->":"Guide5.0.9.$r1"},{"temp=":"$r"},"str",{"->":".^.s"},[{"#n":"$r1"}],"/str","/ev",{"*":".^.^.c-3","flg":18},{"s":["^Well, that's not very reassuring, but I'm still willing to play.",{"->":"$r","var":true},null]}],["ev",{"^->":"Guide5.0.10.$r1"},{"temp=":"$r"},"str",{"->":".^.s"},[{"#n":"$r1"}],"/str","/ev",{"*":".^.^.c-4","flg":18},{"s":["^I'm not interested in playing a game where I can't trust the guide.",{"->":"$r","var":true},null]}],{"c-0":["ev",{"^->":"Guide5.0.c-0.$r2"},"/ev",{"temp=":"$r"},{"->":".^.^.6.s"},[{"#n":"$r2"}],"\n","ev",{"VAR?":"Heresy"},1,"-",{"VAR=":"Heresy","re":true},"/ev","done",{"#f":5}],"c-1":["ev",{"^->":"Guide5.0.c-1.$r2"},"/ev",{"temp=":"$r"},{"->":".^.^.7.s"},[{"#n":"$r2"}],"\n","ev",{"VAR?":"Heresy"},1,"+",{"VAR=":"Heresy","re":true},"/ev","done",{"#f":5}],"c-2":["ev",{"^->":"Guide5.0.c-2.$r2"},"/ev",{"temp=":"$r"},{"->":".^.^.8.s"},[{"#n":"$r2"}],"\n","ev",{"VAR?":"Heresy"},1,"+",{"VAR=":"Heresy","re":true},"/ev","done",{"#f":5}],"c-3":["ev",{"^->":"Guide5.0.c-3.$r2"},"/ev",{"temp=":"$r"},{"->":".^.^.9.s"},[{"#n":"$r2"}],"\n","ev",{"VAR?":"Heresy"},1,"-",{"VAR=":"Heresy","re":true},"/ev","done",{"#f":5}],"c-4":["ev",{"^->":"Guide5.0.c-4.$r2"},"/ev",{"temp=":"$r"},{"->":".^.^.10.s"},[{"#n":"$r2"}],"\n","ev",{"VAR?":"Heresy"},1,"+",{"VAR=":"Heresy","re":true},"/ev","done",{"#f":5}]}],{"#f":1}],"global decl":["ev",10,{"VAR=":"Corruption"},10,{"VAR=":"Lust"},10,{"VAR=":"Wrath"},10,{"VAR=":"Greed"},10,{"VAR=":"Gluttony"},10,{"VAR=":"Heresy"},10,{"VAR=":"Fraud"},10,{"VAR=":"Violence"},10,{"VAR=":"Treachery"},false,{"VAR=":"End"},"/ev","end",null],"#f":1}],"listDefs":{}}